cvutils_IGNchinmay/__init__.py
cvutils_IGNchinmay/algo_utils.py
cvutils_IGNchinmay/clone_utils.py
cvutils_IGNchinmay/config_utils.py
cvutils_IGNchinmay/contour_utils.py
cvutils_IGNchinmay/docker_utils.py
cvutils_IGNchinmay/draw_utils.py
cvutils_IGNchinmay/file_utils.py
cvutils_IGNchinmay/filter_utils.py
cvutils_IGNchinmay/fisheye_utils.py
cvutils_IGNchinmay/geom_utils.py
cvutils_IGNchinmay/gpu_utils.py
cvutils_IGNchinmay/img_utils.py
cvutils_IGNchinmay/json_utils.py
cvutils_IGNchinmay/keyboard_utils.py
cvutils_IGNchinmay/labelme_utils.py
cvutils_IGNchinmay/license_check.py
cvutils_IGNchinmay/mouse_utils.py
cvutils_IGNchinmay/multi_process_utils.py
cvutils_IGNchinmay/show_utils.py
cvutils_IGNchinmay/ssh_utils.py
cvutils_IGNchinmay/system_utils.py
cvutils_IGNchinmay/timer_utils.py
cvutils_IGNchinmay/transform_utils.py
cvutils_IGNchinmay/transfrom_crops.py
cvutils_IGNchinmay/typehint_utils.py
cvutils_IGNchinmay/yaml_utils.py
cvutils_IGNchinmay/autoui_utils/__init__.py
cvutils_IGNchinmay/autoui_utils/autogui_utils.py
cvutils_IGNchinmay/autoui_utils/autotest_recplayback.py
cvutils_IGNchinmay/autoui_utils/calculator_demo.py
cvutils_IGNchinmay/calib_utils/__init__.py
cvutils_IGNchinmay/calib_utils/angle_utils.py
cvutils_IGNchinmay/calib_utils/charuco_mono_calib.py
cvutils_IGNchinmay/calib_utils/charuco_stereo_calib.py
cvutils_IGNchinmay/calib_utils/infer_depth.py
cvutils_IGNchinmay/calib_utils/mono_calib.py
cvutils_IGNchinmay/calib_utils/mono_dump.py
cvutils_IGNchinmay/calib_utils/mono_error_calc.py
cvutils_IGNchinmay/calib_utils/mono_undistort.py
cvutils_IGNchinmay/calib_utils/optimize_depth.py
cvutils_IGNchinmay/calib_utils/point_depth_demo.py
cvutils_IGNchinmay/calib_utils/pose_estimate.py
cvutils_IGNchinmay/calib_utils/rs_crop_dump.py
cvutils_IGNchinmay/calib_utils/stereo_3d_error_calc.py
cvutils_IGNchinmay/calib_utils/stereo_calib.py
cvutils_IGNchinmay/calib_utils/stereo_dump.py
cvutils_IGNchinmay/calib_utils/stereo_error_calc.py
cvutils_IGNchinmay-0.0.5.dist-info/LICENSE.txt
cvutils_IGNchinmay-0.0.5.dist-info/METADATA
cvutils_IGNchinmay-0.0.5.dist-info/WHEEL
cvutils_IGNchinmay-0.0.5.dist-info/top_level.txt
cvutils_IGNchinmay-0.0.5.dist-info/RECORD
